README.rst
setup.py
tornado_qiniu/__init__.py
tornado_qiniu/bucket.py
tornado_qiniu/client.py
tornado_qiniu/common.py
tornado_qiniu/errors.py
tornado_qiniu/interface.py
tornado_qiniu/resource.py
tornado_qiniu/utils.py
tornado_qiniu.egg-info/PKG-INFO
tornado_qiniu.egg-info/SOURCES.txt
tornado_qiniu.egg-info/dependency_links.txt
tornado_qiniu.egg-info/requires.txt
tornado_qiniu.egg-info/top_level.txt
tornado_qiniu/tests/__init__.py
tornado_qiniu/tests/runtests.py
tornado_qiniu/tests/test_resource_load.py