Metadata-Version: 1.1
Name: tornado-qiniu
Version: 1.2
Summary: An asynchronous qiniu cloud storage sdk for tornado
Home-page: https://github.com/free-free/tornaqiniu
Author: HuangBiao
Author-email: 19941222hb@gmail.com
License: MIT
Keywords: tornado,qiniu,sdk
Platform: UNKNOWN
Classifier: Intended Audience :: Developers
Classifier: License :: OSI Approved :: MIT License
Classifier: Programming Language :: Python
Classifier: Programming Language :: Python :: 3
Classifier: Programming Language :: Python :: 3.4
Classifier: Programming Language :: Python :: 3.5
Classifier: Topic :: Software Development :: Libraries :: Python Modules
Classifier: Topic :: Internet :: WWW/HTTP :: Dynamic Content
